object_detection_library/OpCameraUtils.py
object_detection_library/OpImageProcUtils.py
object_detection_library/OpImageUtils.py
object_detection_library/__init__.py
object_detection_library/main.py
object_detection_library/mqtt_client.py
object_detection_library/test.py
object_detection_library-0.4.2.dist-info/METADATA
object_detection_library-0.4.2.dist-info/WHEEL
object_detection_library-0.4.2.dist-info/entry_points.txt
object_detection_library-0.4.2.dist-info/top_level.txt
object_detection_library-0.4.2.dist-info/RECORD
