Metadata-Version: 2.1
Name: object_detection_library
Version: 0.4.2
Summary: A library for YOLOv8 object detection and other utilities.
Home-page: https://github.com/Karthik180304/object-detection
Author: Karthik
Author-email: karthik.shivakkumar@gmail.com
License: MIT
Classifier: Programming Language :: Python :: 3
Classifier: License :: OSI Approved :: MIT License
Classifier: Operating System :: OS Independent
Requires-Python: >=3.6
Requires-Dist: torch
Requires-Dist: ultralytics
Requires-Dist: opencv-python
Requires-Dist: paho-mqtt
Requires-Dist: numpy
Requires-Dist: expecttest
